dependency_metrics/__init__.py
dependency_metrics/constants.py
dependency_metrics/datadog_utils.py
dependency_metrics/exceptions.py
dependency_metrics/metrics.py
dependency_metrics/parsing_utils.py
dependency_metrics/package_managers/__init__.py
dependency_metrics/package_managers/pip.py
dependency_metrics/package_managers/utils.py
dependency_metrics/package_managers/yarn.py
dependency_metrics-0.1.3.dist-info/licenses/LICENSE
dependency_metrics-0.1.3.dist-info/METADATA
dependency_metrics-0.1.3.dist-info/WHEEL
dependency_metrics-0.1.3.dist-info/entry_points.txt
dependency_metrics-0.1.3.dist-info/top_level.txt
dependency_metrics-0.1.3.dist-info/RECORD
