Metadata-Version: 2.4
Name: dependency-metrics
Version: 0.1.3
Summary: Python tool to track outdated dependencies.
Author-email: Dimagi <dev@dimagi.com>
Maintainer-email: Dimagi <dev@dimagi.com>
License: Copyright (c) 2023, Dimagi Inc., and individual contributors.
Project-URL: repository, https://github.com/dimagi/dependency-metrics
Classifier: Development Status :: 3 - Alpha
Classifier: Intended Audience :: Developers
Classifier: License :: OSI Approved :: BSD License
Classifier: Programming Language :: Python
Classifier: Programming Language :: Python :: 3
Classifier: Topic :: Software Development :: Libraries :: Python Modules
License-File: LICENSE
Requires-Dist: requests
Requires-Dist: sh>=2.0.0
Provides-Extra: test
Requires-Dist: freezegun; extra == "test"
Requires-Dist: nose2; extra == "test"
Dynamic: license-file
